textencryptor/Textencryptor.py
textencryptor/__init__.py
textencryptor-0.0.1.dist-info/LICENSE.txt
textencryptor-0.0.1.dist-info/METADATA
textencryptor-0.0.1.dist-info/WHEEL
textencryptor-0.0.1.dist-info/top_level.txt
textencryptor-0.0.1.dist-info/RECORD
