Metadata-Version: 2.1
Name: textencryptor
Version: 0.0.1
Summary: A small package which encrypts plain text
Home-page: https://github.com/andrewmummery/TextEncryptor
Author: Andrew Mummery
Author-email: andrew.mummery.software@gmail.com
License: UNKNOWN
Platform: UNKNOWN
Classifier: Programming Language :: Python :: 3
Classifier: License :: OSI Approved :: MIT License
Classifier: Operating System :: OS Independent
Requires-Python: >=3.6
